dcnum/__init__.py
dcnum/_version.py
dcnum/common.py
dcnum/os_env_st.py
dcnum/external/__init__.py
dcnum/external/skimage_morphology.py
dcnum/feat/__init__.py
dcnum/feat/gate.py
dcnum/feat/queue_event_extractor.py
dcnum/feat/feat_background/__init__.py
dcnum/feat/feat_background/base.py
dcnum/feat/feat_background/bg_copy.py
dcnum/feat/feat_background/bg_roll_median.py
dcnum/feat/feat_background/bg_sparse_median.py
dcnum/feat/feat_brightness/__init__.py
dcnum/feat/feat_brightness/bright_all.py
dcnum/feat/feat_brightness/common.py
dcnum/feat/feat_contour/__init__.py
dcnum/feat/feat_contour/contour.py
dcnum/feat/feat_contour/moments.py
dcnum/feat/feat_contour/volume.py
dcnum/feat/feat_texture/__init__.py
dcnum/feat/feat_texture/common.py
dcnum/feat/feat_texture/tex_all.py
dcnum/logic/__init__.py
dcnum/logic/chunk_slot.py
dcnum/logic/chunk_slot_data.py
dcnum/logic/ctrl.py
dcnum/logic/job.py
dcnum/logic/json_encoder.py
dcnum/logic/slot_register.py
dcnum/logic/universal_worker.py
dcnum/meta/__init__.py
dcnum/meta/paths.py
dcnum/meta/ppid.py
dcnum/read/__init__.py
dcnum/read/cache.py
dcnum/read/const.py
dcnum/read/detect_flicker.py
dcnum/read/hdf5_concat.py
dcnum/read/hdf5_data.py
dcnum/read/mapped.py
dcnum/segm/__init__.py
dcnum/segm/segm_thresh.py
dcnum/segm/segmenter.py
dcnum/segm/segmenter_manager_thread.py
dcnum/segm/segmenter_mpo.py
dcnum/segm/segmenter_sto.py
dcnum/segm/segm_torch/__init__.py
dcnum/segm/segm_torch/segm_torch_base.py
dcnum/segm/segm_torch/segm_torch_mpo.py
dcnum/segm/segm_torch/segm_torch_sto.py
dcnum/segm/segm_torch/torch_model.py
dcnum/segm/segm_torch/torch_postproc.py
dcnum/segm/segm_torch/torch_preproc.py
dcnum/segm/segm_torch/torch_setup.py
dcnum/write/__init__.py
dcnum/write/chunk_writer.py
dcnum/write/event_stash.py
dcnum/write/queue_writer_base.py
dcnum/write/queue_writer_process.py
dcnum/write/queue_writer_thread.py
dcnum/write/writer.py
dcnum-0.29.2.dist-info/licenses/LICENSE
dcnum-0.29.2.dist-info/METADATA
dcnum-0.29.2.dist-info/WHEEL
dcnum-0.29.2.dist-info/top_level.txt
dcnum-0.29.2.dist-info/RECORD
