Metadata-Version: 2.4
Name: dcnum
Version: 0.29.2
Summary: numerics toolbox for imaging deformability cytometry
Author: Maximilian Schlögel, Paul Müller, Raghava Alajangi
Maintainer-email: Paul Müller <dev@craban.de>
License-Expression: MIT
Project-URL: source, https://github.com/DC-Analysis/dcnum
Project-URL: tracker, https://github.com/DC-Analysis/dcnum/issues
Project-URL: documentation, https://dcnum.readthedocs.io/en/stable/
Project-URL: changelog, https://dcnum.readthedocs.io/en/stable/sec_changelog.html
Keywords: RT-DC,deformability,cytometry
Classifier: Operating System :: OS Independent
Classifier: Programming Language :: Python :: 3
Classifier: Topic :: Scientific/Engineering :: Visualization
Classifier: Intended Audience :: Science/Research
Requires-Python: <4,>=3.10
License-File: LICENSE
Requires-Dist: h5py<4,>=3.0.0
Requires-Dist: hdf5plugin<6,>=3.3.1
Requires-Dist: mahotas<2,>=1
Requires-Dist: numba<1,>=0.60
Requires-Dist: numpy<3,>=1.21
Requires-Dist: opencv-python-headless<5,>=4
Requires-Dist: scipy!=1.15.1,!=1.15.2,<2,>=1.8.0
Provides-Extra: torch
Requires-Dist: torch<3,>=2.2; extra == "torch"
Dynamic: license-file
